[
	{
		"username": "YaraRohana",
		"email": "yara.rohana@gmail.com",
		"streetName": "Stella Maris",
		"apartmentNumber": "23",
		"cityName": "Haifa",
		"postalCode": "1234567",
		"phoneNumber": "048392769",
		"password": "pass1",
		"nickname": "yara12",
		"description": "Computer Science student",
		"imageURL": "user-female-icon.png",
		"isConnected": "false"
	},
	{
		"username": "AnanSbeit",
		"email": "anansbeit@gmail.com",
		"streetName": "Rameh1",
		"apartmentNumber": "11",
		"cityName": "Rameh",
		"postalCode": "1234567",
		"phoneNumber": "048392761",
		"password": "pass2",
		"nickname": "anan",
		"description": "Computer Science student",
		"imageURL": "Avatar.png",
		"isConnected": "false"
	},
	{
		"username": "BadiSaliba",
		"email": "badiesa@gmail.com",
		"streetName": "Stella Maris",
		"apartmentNumber": "13",
		"cityName": "Haifa",
		"postalCode": "1234567",
		"phoneNumber": "0522222222",
		"password": "passwd3",
		"nickname": "bido",
		"description": "Computer Science student",
		"imageURL": "Avatar.png",
		"isConnected": "false"
	},
	{
		"username": "ArenRohana",
		"email": "areen@gmail.com",
		"streetName": "222",
		"apartmentNumber": "14",
		"cityName": "Isfiya",
		"postalCode": "1234567",
		"phoneNumber": "0522234522",
		"password": "passwd4",
		"nickname": "3reshe",
		"description": "Computer Science student",
		"imageURL": "user-female-icon.png",
		"isConnected": "false"
	},
	{
		"username": "HaniaOukal",
		"email": "areen@gmail.com",
		"streetName": "222",
		"apartmentNumber": "14",
		"cityName": "Shefa Amr",
		"postalCode": "1234567",
		"phoneNumber": "0522234522",
		"password": "passd5",
		"nickname": "hanhoon",
		"description": "Computer Science student",
		"imageURL": "user-female-icon.png",
		"isConnected": "false"
	},{
			"username": "CoolBoy123",
		"email": "coolboy@gmail.com",
		"streetName": "222",
		"apartmentNumber": "14",
		"cityName": "Shefa Amr",
		"postalCode": "1234567",
		"phoneNumber": "0522234522",
		"password": "passd5",
		"nickname": "coolBoy",
		"description": "Computer Science student",
		"imageURL": "user-female-icon.png",
		"isConnected": "false"
	}
]